{
  "info" : {
    "totalResultsLocal" : 1,
    "totalResultsPC" : -1,
    "total" : 1,
    "first" : 1,
    "last" : 1
  },
  "highlights" : {
    "termsUnion" : [ ]
  },
  "docs" : [ {
    "context" : "L",
    "adaptor" : "Local Search Engine",
    "@id" : "https://na07.alma.exlibrisgroup.com/primaws/rest/pub/pnxs/L/990009645090107871",
    "pnx" : {
      "display" : {
        "source" : [ "Alma" ],
        "type" : [ "book" ],
        "language" : [ "eng" ],
        "title" : [ "Building a national strategy for digital preservation : issues in digital media archiving." ],
        "subject" : [ "Digital preservation" ],
        "format" : [ "iv, 95 p. : ill. ; 28 cm." ],
        "identifier" : [ "$$CISBN$$V1887334912;$$COCLC$$V(OCoLC)49848531" ],
        "creationdate" : [ "2002" ],
        "publisher" : [ "Washington, D.C. : Council on Library and Information Resources and Library of Congress" ],
        "mms" : [ "990009645090107871" ],
        "contributor" : [ "Council on Library and Information Resources.$$QCouncil on Library and Information Resources.", "National Digital Information Infrastructure and Preservation Program (U.S.)$$QNational Digital Information Infrastructure and Preservation Program (U.S.)" ],
        "place" : [ "Washington, D.C. :" ],
        "version" : [ "0" ],
        "lds52" : [ "aleph000964509" ],
        "lds53" : [ "000964509" ],
        "lds60" : [ "\"Commissioned for and sponsored by the National Digital Information Infrastructure and Preservation Program, Library of Congress\"", "\"April 2002\"" ]
      },
      "control" : {
        "sourcerecordid" : [ "990009645090107871" ],
        "recordid" : [ "alma990009645090107871" ],
        "sourceid" : "alma",
        "originalsourceid" : [ "000964509-NYU01" ],
        "sourcesystem" : [ "ILS" ],
        "sourceformat" : [ "MARC21" ],
        "score" : [ "2.593449E-4" ],
        "isDedup" : false
      },
      "addata" : {
        "date" : [ "2002" ],
        "isbn" : [ "1887334912" ],
        "notes" : [ "Includes bibliographical references." ],
        "cop" : [ "Washington, D.C" ],
        "pub" : [ "Council on Library and Information Resources and Library of Congress" ],
        "oclcid" : [ "(ocolc)49848531" ],
        "format" : [ "book" ],
        "genre" : [ "book" ],
        "ristype" : [ "BOOK" ],
        "btitle" : [ "Building a national strategy for digital preservation : issues in digital media archiving." ]
      },
      "sort" : {
        "title" : [ "Building a national strategy for digital preservation : issues in digital media archiving." ],
        "author" : [ "Council on Library and Information Resources." ],
        "creationdate" : [ "2002" ]
      },
      "facets" : {
        "frbrtype" : [ "6" ]
      }
    },
    "delivery" : {
      "bestlocation" : null,
      "holding" : null,
      "electronicServices" : null,
      "additionalElectronicServices" : null,
      "filteredByGroupServices" : null,
      "quickAccessService" : null,
      "deliveryCategory" : [ "Alma-P" ],
      "serviceMode" : [ "howovp" ],
      "availability" : [ "no_inventory" ],
      "availabilityLinks" : [ "detailsgetit1" ],
      "availabilityLinksUrl" : [ "detailsgetit1" ],
      "displayedAvailability" : "no_inventory",
      "displayLocation" : null,
      "additionalLocations" : null,
      "physicalItemTextCodes" : null,
      "feDisplayOtherLocations" : null,
      "almaInstitutionsList" : [ {
        "getitLink" : [ {
          "displayText" : "Alma-P",
          "linkRecordId" : "990009645090107871"
        } ],
        "instCode" : "01NYU_INST",
        "instName" : "New York University - New York",
        "instId" : "7876",
        "availabilityStatus" : "available_in_institution",
        "envURL" : ""
      } ],
      "recordInstitutionCode" : null,
      "recordOwner" : "01NYU_NETWORK",
      "hasFilteredServices" : null,
      "digitalAuxiliaryMode" : false,
      "hideResourceSharing" : false,
      "sharedDigitalCandidates" : null,
      "consolidatedCoverage" : null,
      "electronicContextObjectId" : null,
      "GetIt1" : [ {
        "category" : "Alma-P",
        "links" : [ {
          "isLinktoOnline" : false,
          "getItTabText" : "service_howtogetit",
          "adaptorid" : "ALMA_01",
          "ilsApiId" : "",
          "link" : "HowToGetIt",
          "inst4opac" : "",
          "displayText" : null,
          "@id" : "_:0"
        } ]
      } ],
      "physicalServiceId" : null,
      "link" : [ {
        "@id" : ":_0",
        "linkType" : "thumbnail",
        "linkURL" : "https://proxy-na.hosted.exlibrisgroup.com/exl_rewrite/books.google.com/books?bibkeys=ISBN:1887334912,OCLC:,LCCN:&jscmd=viewapi&callback=updateGBSCover",
        "displayLabel" : "thumbnail"
      } ],
      "hasD" : null
    },
    "enrichment" : {
      "virtualBrowseObject" : {
        "isVirtualBrowseEnabled" : false,
        "callNumber" : "",
        "callNumberBrowseField" : ""
      },
      "bibVirtualBrowseObject" : {
        "isVirtualBrowseEnabled" : true,
        "callNumber" : "z000000000681.000000000003.d000000000053b000000000085000000002002",
        "callNumberBrowseField" : "LOCAL_CL_09X"
      }
    }
  } ],
  "timelog" : {
    "BUILD_RESULTS_RETRIVE_FROM_DB" : "15",
    "CALL_SOLR_GET_IDS_LIST" : "64",
    "PRIMA_LOCAL_SEARCH_SET_AVALIABILITY" : "23",
    "RETRIVE_COLLECTION_DISCOVERY_INFO" : "2",
    "RETRIVE_FROM_DB_COURSE_INFO" : "3",
    "RETRIVE_FROM_DB_RECORDS" : "6",
    "RETRIVE_FROM_DB_RELATIONS" : "2",
    "SET_AVAILABILTY_GET_LIBRARY_DETAILS" : "21",
    "SET_AVAILABILTY_HOLDING_DEDUPS" : "2",
    "PRIMA_LOCAL_INFO_FACETS_BUILD_DOCS_HIGHLIGHTS" : "9",
    "PRIMA_LOCAL_SEARCH_TOTAL" : "122",
    "BUILD_BLEND_AND_CACHE_RESULTS" : 0,
    "BUILD_COMBINED_RESULTS_MAP" : 151,
    "COMBINED_SEARCH_TIME" : 154,
    "PROCESS_COMBINED_RESULTS" : 0,
    "FEATURED_SEARCH_TIME" : 1
  },
  "facets" : [ {
    "name" : "lang",
    "values" : [ {
      "value" : "eng",
      "count" : "1"
    } ]
  }, {
    "name" : "creationdate",
    "values" : [ {
      "value" : "2002",
      "count" : "1"
    } ]
  }, {
    "name" : "rtype",
    "values" : [ {
      "value" : "books",
      "count" : "1"
    } ]
  }, {
    "name" : "topic",
    "values" : [ {
      "value" : "Digital Preservation",
      "count" : "1"
    } ]
  }, {
    "name" : "creator",
    "values" : [ {
      "value" : "Council On Library And Information Resources",
      "count" : "1"
    }, {
      "value" : "National Digital Information Infrastructure And Preservation Program U S",
      "count" : "1"
    } ]
  }, {
    "name" : "library",
    "values" : [ {
      "value" : "7876–163048130007876",
      "count" : "1"
    } ]
  }, {
    "name" : "tlevel",
    "values" : [ {
      "value" : "available_p",
      "count" : "1"
    } ]
  }, {
    "name" : "institution",
    "values" : [ {
      "value" : "7876",
      "count" : "1"
    } ]
  } ]
}